apollo/__init__.py
apollo/apollo_client.py
apollo/feature_switch.py
apollo/open_setting.py
apollolib/__init__.py
apollolib/apollo_client.py
apollolib/feature_switch.py
apollolib/open_setting.py
featurepalette/__init__.py
featurepalette/featurepalette_client.py
featurepalette/errno/__init__.py
featurepalette/errno/constants.py
featurepalette/errno/ttypes.py
featurepalette/response/__init__.py
featurepalette/response/constants.py
featurepalette/response/ttypes.py
featurepalette/service/FeaturePalette.py
featurepalette/service/__init__.py
featurepalette/service/constants.py
featurepalette/service/ttypes.py
featurepalette/trace/__init__.py
featurepalette/trace/constants.py
featurepalette/trace/ttypes.py
util/__init__.py
util/log.py
util/metric.py
util/path.py
util/service.py
util/time.py
dengineclient-4.0.1.dist-info/METADATA
dengineclient-4.0.1.dist-info/WHEEL
dengineclient-4.0.1.dist-info/top_level.txt
dengineclient-4.0.1.dist-info/RECORD
