Metadata-Version: 2.1
Name: dengineclient
Version: 4.0.1
Summary: apollo and featurepalette client
Home-page: UNKNOWN
Author: zhangmanni
Author-email: zhangmanni@didiglobal.com
License: UNKNOWN
Platform: UNKNOWN
Classifier: Programming Language :: Python :: 3
Classifier: License :: OSI Approved :: MIT License
Classifier: Operating System :: OS Independent
